regx/__init__.py
regx/__main__.py
regx/engine/__init__.py
regx-1.0.0.data/scripts/regx
regx-1.0.0.dist-info/DESCRIPTION.rst
regx-1.0.0.dist-info/METADATA
regx-1.0.0.dist-info/RECORD
regx-1.0.0.dist-info/WHEEL
regx-1.0.0.dist-info/metadata.json
regx-1.0.0.dist-info/top_level.txt
test/__init__.py
test/engine/__init__.py
test/engine/test_pattern.py
